mongodb_connect/__init__.py
mongodb_connect/mongo_crud.py
Channudam_DB_Custome_Connection-0.0.1.dist-info/LICENSE
Channudam_DB_Custome_Connection-0.0.1.dist-info/METADATA
Channudam_DB_Custome_Connection-0.0.1.dist-info/WHEEL
Channudam_DB_Custome_Connection-0.0.1.dist-info/top_level.txt
Channudam_DB_Custome_Connection-0.0.1.dist-info/RECORD
